{"textures":{"0":"modelengine:entity/villager_ape_2"},"elements":[{"name":"cube","from":[5.0,9.255736,5.66],"to":[11.0,17.055737,11.660001],"rotation":{"angle":0.0,"axis":"x","origin":[5.0,-3.3442645,4.46]},"faces":{"down":{"uv":[3.75,1.25,2.5,2.5],"rotation":0,"texture":"#0","tintindex":0},"east":{"uv":[1.25,0.0,2.5,1.625],"rotation":0,"texture":"#0","tintindex":0},"north":{"uv":[0.0,0.0,1.25,1.625],"rotation":0,"texture":"#0","tintindex":0},"south":{"uv":[0.0,1.625,1.25,3.25],"rotation":0,"texture":"#0","tintindex":0},"up":{"uv":[3.75,1.25,2.5,0.0],"rotation":0,"texture":"#0","tintindex":0},"west":{"uv":[1.25,1.625,2.5,3.25],"rotation":0,"texture":"#0","tintindex":0}}},{"name":"cube","from":[5.0,13.455736,5.06],"to":[11.0,16.455736,5.66],"rotation":{"angle":0.0,"axis":"x","origin":[5.0,-3.3442645,4.46]},"faces":{"down":{"uv":[7.25,0.125,6.0,0.25],"rotation":0,"texture":"#0","tintindex":0},"east":{"uv":[4.375,5.875,4.5,6.5],"rotation":0,"texture":"#0","tintindex":0},"north":{"uv":[6.25,2.25,7.5,2.875],"rotation":0,"texture":"#0","tintindex":0},"south":{"uv":[6.25,4.375,7.5,5.0],"rotation":0,"texture":"#0","tintindex":0},"up":{"uv":[7.25,0.125,6.0,0.0],"rotation":0,"texture":"#0","tintindex":0},"west":{"uv":[1.5,6.375,1.625,7.0],"rotation":0,"texture":"#0","tintindex":0}}},{"name":"cube","from":[4.7,16.455736,5.3599997],"to":[11.3,18.855736,11.96],"rotation":{"angle":0.0,"axis":"x","origin":[4.7,-3.3442645,4.46]},"faces":{"down":{"uv":[1.375,6.0,0.0,7.375],"rotation":0,"texture":"#0","tintindex":0},"east":{"uv":[7.0,5.0,8.375,5.5],"rotation":0,"texture":"#0","tintindex":0},"north":{"uv":[7.0,1.375,8.375,1.875],"rotation":0,"texture":"#0","tintindex":0},"south":{"uv":[4.5,7.25,5.875,7.75],"rotation":0,"texture":"#0","tintindex":0},"up":{"uv":[6.625,7.25,5.25,5.875],"rotation":0,"texture":"#0","tintindex":0},"west":{"uv":[0.0,7.375,1.375,7.875],"rotation":0,"texture":"#0","tintindex":0}}},{"name":"cube","from":[4.3999996,11.055737,5.3599997],"to":[5.0,16.455736,11.96],"rotation":{"angle":0.0,"axis":"x","origin":[4.7,-3.3442645,4.46]},"faces":{"down":{"uv":[2.375,6.25,2.25,7.625],"rotation":0,"texture":"#0","tintindex":0},"east":{"uv":[6.125,3.0,7.5,4.125],"rotation":0,"texture":"#0","tintindex":0},"north":{"uv":[6.5,7.25,6.625,8.375],"rotation":0,"texture":"#0","tintindex":0},"south":{"uv":[1.875,7.375,2.0,8.5],"rotation":0,"texture":"#0","tintindex":0},"up":{"uv":[4.625,7.25,4.5,5.875],"rotation":0,"texture":"#0","tintindex":0},"west":{"uv":[3.125,6.5,4.5,7.625],"rotation":0,"texture":"#0","tintindex":0}}},{"name":"cube","from":[3.7999997,11.055737,7.16],"to":[4.3999996,16.455736,9.56],"rotation":{"angle":0.0,"axis":"x","origin":[4.7,-3.3442645,4.46]},"faces":{"down":{"uv":[1.75,6.875,1.625,7.375],"rotation":0,"texture":"#0","tintindex":0},"east":{"uv":[7.375,0.0,7.875,1.125],"rotation":0,"texture":"#0","tintindex":0},"north":{"uv":[5.125,6.0,5.25,7.125],"rotation":0,"texture":"#0","tintindex":0},"south":{"uv":[6.375,7.25,6.5,8.375],"rotation":0,"texture":"#0","tintindex":0},"up":{"uv":[4.875,6.875,4.75,6.375],"rotation":0,"texture":"#0","tintindex":0},"west":{"uv":[1.375,7.375,1.875,8.5],"rotation":0,"texture":"#0","tintindex":0}}},{"name":"cube","from":[11.6,11.055737,7.16],"to":[12.2,16.455736,9.56],"rotation":{"angle":0.0,"axis":"x","origin":[11.3,-3.3442645,4.46]},"faces":{"down":{"uv":[4.75,6.375,4.625,6.875],"rotation":0,"texture":"#0","tintindex":0},"east":{"uv":[1.75,6.25,2.25,7.375],"rotation":0,"texture":"#0","tintindex":0},"north":{"uv":[4.875,6.0,5.0,7.125],"rotation":0,"texture":"#0","tintindex":0},"south":{"uv":[5.0,6.0,5.125,7.125],"rotation":0,"texture":"#0","tintindex":0},"up":{"uv":[1.75,6.875,1.625,6.375],"rotation":0,"texture":"#0","tintindex":0},"west":{"uv":[5.875,7.25,6.375,8.375],"rotation":0,"texture":"#0","tintindex":0}}},{"name":"cube","from":[11.0,11.055737,5.3599997],"to":[11.6,16.455736,11.96],"rotation":{"angle":0.0,"axis":"x","origin":[11.3,-3.3442645,4.46]},"faces":{"down":{"uv":[2.625,7.0,2.5,8.375],"rotation":0,"texture":"#0","tintindex":0},"east":{"uv":[6.625,5.5,8.0,6.625],"rotation":0,"texture":"#0","tintindex":0},"north":{"uv":[2.0,7.375,2.125,8.5],"rotation":0,"texture":"#0","tintindex":0},"south":{"uv":[2.125,7.375,2.25,8.5],"rotation":0,"texture":"#0","tintindex":0},"up":{"uv":[2.5,7.625,2.375,6.25],"rotation":0,"texture":"#0","tintindex":0},"west":{"uv":[6.625,6.625,8.0,7.75],"rotation":0,"texture":"#0","tintindex":0}}},{"name":"cube","from":[5.0,12.855737,5.06],"to":[6.8,13.455736,5.66],"rotation":{"angle":0.0,"axis":"x","origin":[5.0,-3.3442645,4.46]},"faces":{"down":{"uv":[6.25,5.0,5.875,5.125],"rotation":0,"texture":"#0","tintindex":0},"east":{"uv":[4.625,5.125,4.75,5.25],"rotation":0,"texture":"#0","tintindex":0},"north":{"uv":[5.875,4.75,6.25,4.875],"rotation":0,"texture":"#0","tintindex":0},"south":{"uv":[4.875,5.875,5.25,6.0],"rotation":0,"texture":"#0","tintindex":0},"up":{"uv":[6.25,5.0,5.875,4.875],"rotation":0,"texture":"#0","tintindex":0},"west":{"uv":[5.125,5.25,5.25,5.375],"rotation":0,"texture":"#0","tintindex":0}}},{"name":"cube","from":[9.2,12.855737,5.06],"to":[11.0,13.455736,5.66],"rotation":{"angle":0.0,"axis":"x","origin":[11.0,-3.3442645,4.46]},"faces":{"down":{"uv":[6.25,4.625,5.875,4.75],"rotation":0,"texture":"#0","tintindex":0},"east":{"uv":[3.125,4.875,3.25,5.0],"rotation":0,"texture":"#0","tintindex":0},"north":{"uv":[5.125,0.75,5.5,0.875],"rotation":0,"texture":"#0","tintindex":0},"south":{"uv":[5.875,4.375,6.25,4.5],"rotation":0,"texture":"#0","tintindex":0},"up":{"uv":[6.25,4.625,5.875,4.5],"rotation":0,"texture":"#0","tintindex":0},"west":{"uv":[3.125,5.0,3.25,5.125],"rotation":0,"texture":"#0","tintindex":0}}},{"name":"cube","from":[6.5,9.255736,4.46],"to":[9.5,13.455736,5.66],"rotation":{"angle":0.0,"axis":"x","origin":[6.5,-3.3442645,4.46]},"faces":{"down":{"uv":[6.125,3.25,5.5,3.5],"rotation":0,"texture":"#0","tintindex":0},"east":{"uv":[2.875,5.25,3.125,6.125],"rotation":0,"texture":"#0","tintindex":0},"north":{"uv":[2.5,4.375,3.125,5.25],"rotation":0,"texture":"#0","tintindex":0},"south":{"uv":[4.5,0.0,5.125,0.875],"rotation":0,"texture":"#0","tintindex":0},"up":{"uv":[6.125,3.25,5.5,3.0],"rotation":0,"texture":"#0","tintindex":0},"west":{"uv":[1.5,5.5,1.75,6.375],"rotation":0,"texture":"#0","tintindex":0}}},{"name":"cube","from":[2.8999999,11.355737,8.06],"to":[6.5,14.955736,9.26],"rotation":{"angle":45.0,"axis":"z","origin":[3.4999998,12.855737,8.66]},"faces":{"down":{"uv":[6.25,2.25,5.5,2.5],"rotation":0,"texture":"#0","tintindex":0},"east":{"uv":[5.5,1.5,5.75,2.25],"rotation":0,"texture":"#0","tintindex":0},"north":{"uv":[2.5,3.625,3.25,4.375],"rotation":0,"texture":"#0","tintindex":0},"south":{"uv":[3.75,0.0,4.5,0.75],"rotation":0,"texture":"#0","tintindex":0},"up":{"uv":[4.5,2.5,3.75,2.25],"rotation":0,"texture":"#0","tintindex":0},"west":{"uv":[1.75,5.5,2.0,6.25],"rotation":0,"texture":"#0","tintindex":0}}},{"name":"cube","from":[9.5,11.355737,8.06],"to":[13.1,14.955736,9.26],"rotation":{"angle":-45.0,"axis":"z","origin":[12.5,12.855737,8.66]},"faces":{"down":{"uv":[6.25,2.75,5.5,3.0],"rotation":0,"texture":"#0","tintindex":0},"east":{"uv":[2.0,5.5,2.25,6.25],"rotation":0,"texture":"#0","tintindex":0},"north":{"uv":[3.75,0.75,4.5,1.5],"rotation":0,"texture":"#0","tintindex":0},"south":{"uv":[3.75,1.5,4.5,2.25],"rotation":0,"texture":"#0","tintindex":0},"up":{"uv":[6.25,2.75,5.5,2.5],"rotation":0,"texture":"#0","tintindex":0},"west":{"uv":[2.25,5.5,2.5,6.25],"rotation":0,"texture":"#0","tintindex":0}}},{"name":"cube","from":[7.4,8.055737,8.360001],"to":[8.6,9.255736,9.56],"rotation":{"angle":0.0,"axis":"x","origin":[7.4,-3.9442644,7.16]},"faces":{"down":{"uv":[5.875,4.75,5.625,5.0],"rotation":0,"texture":"#0","tintindex":0},"east":{"uv":[4.5,3.5,4.75,3.75],"rotation":0,"texture":"#0","tintindex":0},"north":{"uv":[3.25,3.625,3.5,3.875],"rotation":0,"texture":"#0","tintindex":0},"south":{"uv":[4.5,3.75,4.75,4.0],"rotation":0,"texture":"#0","tintindex":0},"up":{"uv":[5.875,4.75,5.625,4.5],"rotation":0,"texture":"#0","tintindex":0},"west":{"uv":[5.625,4.25,5.875,4.5],"rotation":0,"texture":"#0","tintindex":0}}}],"display":{"head":{"translation":[0.0,-6.4,0.0],"rotation":[0.0,0.0,0.0],"scale":[3.8095,3.8095,3.8095]}}}