{"textures":{"0":"modelengine:entity/archer"},"elements":[{"name":"left_arm","from":[8.0,7.1,7.04],"to":[12.2,8.9,8.84],"rotation":{"angle":0.0,"axis":"x","origin":[1.9999998,7.1,7.64]},"faces":{"down":{"uv":[9.25,8.5,7.5,9.25],"rotation":0,"texture":"#0","tintindex":0},"east":{"uv":[9.5,6.0,10.25,6.75],"rotation":0,"texture":"#0","tintindex":0},"north":{"uv":[4.0,8.25,5.75,9.0],"rotation":0,"texture":"#0","tintindex":0},"south":{"uv":[5.75,8.25,7.5,9.0],"rotation":0,"texture":"#0","tintindex":0},"up":{"uv":[1.75,9.25,0.0,8.5],"rotation":0,"texture":"#0","tintindex":0},"west":{"uv":[9.25,9.5,10.0,10.25],"rotation":0,"texture":"#0","tintindex":0}}}],"display":{"head":{"translation":[0.0,-6.4,0.0],"rotation":[0.0,0.0,0.0],"scale":[3.8095,3.8095,3.8095]}}}